pants/__init__.py
pants/testutil/__init__.py
pants/testutil/debug_adapter_util.py
pants/testutil/option_util.py
pants/testutil/pants_integration_test.py
pants/testutil/process_util.py
pants/testutil/py.typed
pants/testutil/pytest_util.py
pants/testutil/python_interpreter_selection.py
pants/testutil/python_rule_runner.py
pants/testutil/rule_runner.py
pants/testutil/skip_utils.py
pantsbuild.pants.testutil-2.17.1.dist-info/METADATA
pantsbuild.pants.testutil-2.17.1.dist-info/WHEEL
pantsbuild.pants.testutil-2.17.1.dist-info/namespace_packages.txt
pantsbuild.pants.testutil-2.17.1.dist-info/top_level.txt
pantsbuild.pants.testutil-2.17.1.dist-info/zip-safe
pantsbuild.pants.testutil-2.17.1.dist-info/RECORD
