Metadata-Version: 2.1
Name: pantsbuild.pants.testutil
Version: 2.17.1
Summary: Test support for writing Pants plugins.
Home-page: https://github.com/pantsbuild/pants
License: Apache License, Version 2.0
Project-URL: Documentation, https://www.pantsbuild.org/
Project-URL: Source, https://github.com/pantsbuild/pants
Project-URL: Tracker, https://github.com/pantsbuild/pants/issues
Project-URL: Changelog, https://www.pantsbuild.org/docs/changelog
Project-URL: Twitter, https://twitter.com/pantsbuild
Project-URL: Slack, https://www.pantsbuild.org/docs/getting-help
Project-URL: YouTube, https://www.youtube.com/channel/UCCcfCbDqtqlCkFEuENsHlbQ
Project-URL: Mailing lists, https://www.pantsbuild.org/docs/getting-help
Classifier: Intended Audience :: Developers
Classifier: License :: OSI Approved :: Apache Software License
Classifier: Operating System :: MacOS :: MacOS X
Classifier: Operating System :: POSIX :: Linux
Classifier: Programming Language :: Python
Classifier: Topic :: Software Development :: Build Tools
Classifier: Topic :: Software Development :: Testing
Requires-Python: >=3.7,<3.10
Requires-Dist: pantsbuild.pants (==2.17.1)
Requires-Dist: pytest (<7.1.0,>=6.2.4)
